defargs/__init__.py
defargs/field.py
defargs/parser.py
defargs/struct.py
defargs-0.1.0.dist-info/LICENSE
defargs-0.1.0.dist-info/METADATA
defargs-0.1.0.dist-info/WHEEL
defargs-0.1.0.dist-info/top_level.txt
defargs-0.1.0.dist-info/RECORD
